{
"meta":{"test_sets":[],"test_metrics":[],"learn_metrics":[{"best_value":"Min","name":"RMSE"}],"launch_mode":"Train","parameters":"","iteration_count":100,"learn_sets":["learn"],"name":"experiment"},
"iterations":[
{"learn":[0.3943913045],"iteration":0,"passed_time":0.01249064939,"remaining_time":1.23657429},
{"learn":[0.3877483772],"iteration":1,"passed_time":0.01472413134,"remaining_time":0.7214824357},
{"learn":[0.381982704],"iteration":2,"passed_time":0.01700149972,"remaining_time":0.5497151576},
{"learn":[0.3774580906],"iteration":3,"passed_time":0.01907248148,"remaining_time":0.4577395556},
{"learn":[0.3729883771],"iteration":4,"passed_time":0.02115765372,"remaining_time":0.4019954207},
{"learn":[0.3692209108],"iteration":5,"passed_time":0.02311061151,"remaining_time":0.362066247},
{"learn":[0.3662531432],"iteration":6,"passed_time":0.02519638506,"remaining_time":0.334751973},
{"learn":[0.3633144306],"iteration":7,"passed_time":0.02804616271,"remaining_time":0.3225308712},
{"learn":[0.3611553467],"iteration":8,"passed_time":0.03053195308,"remaining_time":0.30871197},
{"learn":[0.35914708],"iteration":9,"passed_time":0.03275660599,"remaining_time":0.2948094539},
{"learn":[0.3575900445],"iteration":10,"passed_time":0.03497824715,"remaining_time":0.2830058179},
{"learn":[0.3564373006],"iteration":11,"passed_time":0.03709001735,"remaining_time":0.2719934606},
{"learn":[0.3547976564],"iteration":12,"passed_time":0.03920286566,"remaining_time":0.2623576394},
{"learn":[0.3538138386],"iteration":13,"passed_time":0.04126372191,"remaining_time":0.2534771489},
{"learn":[0.3526054639],"iteration":14,"passed_time":0.04410179605,"remaining_time":0.2499101776},
{"learn":[0.3517224707],"iteration":15,"passed_time":0.04649605046,"remaining_time":0.2441042649},
{"learn":[0.3509146979],"iteration":16,"passed_time":0.04870766025,"remaining_time":0.2378079883},
{"learn":[0.3503508753],"iteration":17,"passed_time":0.05089732349,"remaining_time":0.2318655848},
{"learn":[0.349451171],"iteration":18,"passed_time":0.05309182794,"remaining_time":0.2263388454},
{"learn":[0.3488464934],"iteration":19,"passed_time":0.05528415003,"remaining_time":0.2211366001},
{"learn":[0.3483552084],"iteration":20,"passed_time":0.05739544464,"remaining_time":0.2159161965},
{"learn":[0.3479468722],"iteration":21,"passed_time":0.06024942574,"remaining_time":0.2136116004},
{"learn":[0.3475743161],"iteration":22,"passed_time":0.06270018635,"remaining_time":0.2099093195},
{"learn":[0.3472784547],"iteration":23,"passed_time":0.06501238374,"remaining_time":0.2058725485},
{"learn":[0.3468967068],"iteration":24,"passed_time":0.06733705574,"remaining_time":0.2020111672},
{"learn":[0.3465796206],"iteration":25,"passed_time":0.06965619562,"remaining_time":0.1982522491},
{"learn":[0.346049049],"iteration":26,"passed_time":0.07196882153,"remaining_time":0.1945823693},
{"learn":[0.3457004173],"iteration":27,"passed_time":0.07421310744,"remaining_time":0.1908337049},
{"learn":[0.3454005315],"iteration":28,"passed_time":0.0769206581,"remaining_time":0.1883229905},
{"learn":[0.3449500162],"iteration":29,"passed_time":0.07920720173,"remaining_time":0.184816804},
{"learn":[0.3447110345],"iteration":30,"passed_time":0.0814053159,"remaining_time":0.1811924773},
{"learn":[0.3445053205],"iteration":31,"passed_time":0.08367360439,"remaining_time":0.1778064093},
{"learn":[0.3443010456],"iteration":32,"passed_time":0.08581348161,"remaining_time":0.1742273718},
{"learn":[0.3438426256],"iteration":33,"passed_time":0.08796409234,"remaining_time":0.1707538263},
{"learn":[0.3435525722],"iteration":34,"passed_time":0.09032979937,"remaining_time":0.1677553417},
{"learn":[0.343186924],"iteration":35,"passed_time":0.09312911133,"remaining_time":0.1655628646},
{"learn":[0.3430428495],"iteration":36,"passed_time":0.09555817714,"remaining_time":0.1627071665},
{"learn":[0.3427289351],"iteration":37,"passed_time":0.098093957,"remaining_time":0.1600480351},
{"learn":[0.3424988186],"iteration":38,"passed_time":0.1002451985,"remaining_time":0.156793772},
{"learn":[0.3423017584],"iteration":39,"passed_time":0.1024977677,"remaining_time":0.1537466516},
{"learn":[0.3421360516],"iteration":40,"passed_time":0.1044925626,"remaining_time":0.1503673462},
{"learn":[0.3419717504],"iteration":41,"passed_time":0.106759728,"remaining_time":0.1474301006},
{"learn":[0.341764673],"iteration":42,"passed_time":0.1096547193,"remaining_time":0.1453562558},
{"learn":[0.3416566201],"iteration":43,"passed_time":0.1119148198,"remaining_time":0.1424370434},
{"learn":[0.3414365438],"iteration":44,"passed_time":0.1141060125,"remaining_time":0.1394629041},
{"learn":[0.3412721794],"iteration":45,"passed_time":0.1164068674,"remaining_time":0.13665154},
{"learn":[0.3411325989],"iteration":46,"passed_time":0.1185523925,"remaining_time":0.1336867405},
{"learn":[0.3408946428],"iteration":47,"passed_time":0.1208260628,"remaining_time":0.1308949013},
{"learn":[0.3407853962],"iteration":48,"passed_time":0.1235047681,"remaining_time":0.1285457791},
{"learn":[0.3406094934],"iteration":49,"passed_time":0.1264370207,"remaining_time":0.1264370207},
{"learn":[0.3404393954],"iteration":50,"passed_time":0.1285795637,"remaining_time":0.1235372279},
{"learn":[0.3401858223],"iteration":51,"passed_time":0.1306787017,"remaining_time":0.1206264939},
{"learn":[0.340012429],"iteration":52,"passed_time":0.1328069334,"remaining_time":0.1177721862},
{"learn":[0.3397568181],"iteration":53,"passed_time":0.1351782272,"remaining_time":0.1151518232},
{"learn":[0.339533982],"iteration":54,"passed_time":0.1373710003,"remaining_time":0.1123944548},
{"learn":[0.3393154374],"iteration":55,"passed_time":0.142223239,"remaining_time":0.1117468307},
{"learn":[0.3391583506],"iteration":56,"passed_time":0.1457656988,"remaining_time":0.1099635973},
{"learn":[0.3390410562],"iteration":57,"passed_time":0.1479983009,"remaining_time":0.1071711834},
{"learn":[0.3389509705],"iteration":58,"passed_time":0.1499487632,"remaining_time":0.1042016829},
{"learn":[0.3386986795],"iteration":59,"passed_time":0.1521407121,"remaining_time":0.1014271414},
{"learn":[0.3384787287],"iteration":60,"passed_time":0.1544325121,"remaining_time":0.09873554051},
{"learn":[0.3383293992],"iteration":61,"passed_time":0.1568661828,"remaining_time":0.09614378947},
{"learn":[0.3382075583],"iteration":62,"passed_time":0.1589618231,"remaining_time":0.09335853105},
{"learn":[0.3379817751],"iteration":63,"passed_time":0.1610282595,"remaining_time":0.09057839596},
{"learn":[0.3378329338],"iteration":64,"passed_time":0.1631124101,"remaining_time":0.08782975928},
{"learn":[0.3377303346],"iteration":65,"passed_time":0.1651712097,"remaining_time":0.08508819895},
{"learn":[0.3375591057],"iteration":66,"passed_time":0.1673155513,"remaining_time":0.08240915212},
{"learn":[0.3374442031],"iteration":67,"passed_time":0.1694052638,"remaining_time":0.07972012412},
{"learn":[0.3373060324],"iteration":68,"passed_time":0.171816007,"remaining_time":0.0771926988},
{"learn":[0.3371897343],"iteration":69,"passed_time":0.1740866179,"remaining_time":0.07460855051},
{"learn":[0.337036279],"iteration":70,"passed_time":0.1761459061,"remaining_time":0.0719469194},
{"learn":[0.3368994609],"iteration":71,"passed_time":0.1781163628,"remaining_time":0.06926747444},
{"learn":[0.3367218368],"iteration":72,"passed_time":0.1800787962,"remaining_time":0.06660448628},
{"learn":[0.3366133279],"iteration":73,"passed_time":0.1820633678,"remaining_time":0.06396821031},
{"learn":[0.3365136578],"iteration":74,"passed_time":0.1841914544,"remaining_time":0.06139715145},
{"learn":[0.336341359],"iteration":75,"passed_time":0.1861496138,"remaining_time":0.05878408858},
{"learn":[0.3361731215],"iteration":76,"passed_time":0.189260265,"remaining_time":0.05653228696},
{"learn":[0.3360073549],"iteration":77,"passed_time":0.1915259129,"remaining_time":0.05402012928},
{"learn":[0.3357970607],"iteration":78,"passed_time":0.1934591976,"remaining_time":0.05142586265},
{"learn":[0.3356449399],"iteration":79,"passed_time":0.1954365588,"remaining_time":0.04885913971},
{"learn":[0.3355620538],"iteration":80,"passed_time":0.1974516576,"remaining_time":0.04631582091},
{"learn":[0.3354837652],"iteration":81,"passed_time":0.1994890904,"remaining_time":0.04379028814},
{"learn":[0.3353796347],"iteration":82,"passed_time":0.2017465852,"remaining_time":0.04132158975},
{"learn":[0.3352790602],"iteration":83,"passed_time":0.2045729061,"remaining_time":0.03896626782},
{"learn":[0.3351282016],"iteration":84,"passed_time":0.2068190214,"remaining_time":0.03649747437},
{"learn":[0.3349865321],"iteration":85,"passed_time":0.2088632841,"remaining_time":0.03400099973},
{"learn":[0.3348904498],"iteration":86,"passed_time":0.2109458512,"remaining_time":0.03152064443},
{"learn":[0.3347833776],"iteration":87,"passed_time":0.212970882,"remaining_time":0.02904148391},
{"learn":[0.3345840682],"iteration":88,"passed_time":0.2151533477,"remaining_time":0.02659198679},
{"learn":[0.334484864],"iteration":89,"passed_time":0.217186441,"remaining_time":0.02413182678},
{"learn":[0.3343559115],"iteration":90,"passed_time":0.2198928889,"remaining_time":0.02174764836},
{"learn":[0.3341578643],"iteration":91,"passed_time":0.2222825733,"remaining_time":0.01932891942},
{"learn":[0.3340370098],"iteration":92,"passed_time":0.224471709,"remaining_time":0.01689572004},
{"learn":[0.3338221367],"iteration":93,"passed_time":0.2266282525,"remaining_time":0.01446563314},
{"learn":[0.3337167634],"iteration":94,"passed_time":0.2287584585,"remaining_time":0.01203991887},
{"learn":[0.3336665718],"iteration":95,"passed_time":0.2308356104,"remaining_time":0.009618150435},
{"learn":[0.3335205408],"iteration":96,"passed_time":0.2330161498,"remaining_time":0.007206685044},
{"learn":[0.3333144687],"iteration":97,"passed_time":0.2367611377,"remaining_time":0.004831859953},
{"learn":[0.3331558732],"iteration":98,"passed_time":0.2393076656,"remaining_time":0.002417249148},
{"learn":[0.3329436374],"iteration":99,"passed_time":0.2416599584,"remaining_time":0}
]}